odoo/addons/account_invoice_check_picking_date/README.rst
odoo/addons/account_invoice_check_picking_date/__init__.py
odoo/addons/account_invoice_check_picking_date/__manifest__.py
odoo/addons/account_invoice_check_picking_date/i18n/account_invoice_check_picking_date.pot
odoo/addons/account_invoice_check_picking_date/i18n/es.po
odoo/addons/account_invoice_check_picking_date/models/__init__.py
odoo/addons/account_invoice_check_picking_date/models/account_move.py
odoo/addons/account_invoice_check_picking_date/readme/CONTRIBUTORS.rst
odoo/addons/account_invoice_check_picking_date/readme/DESCRIPTION.rst
odoo/addons/account_invoice_check_picking_date/readme/INSTALL.rst
odoo/addons/account_invoice_check_picking_date/readme/USAGE.rst
odoo/addons/account_invoice_check_picking_date/static/description/icon.png
odoo/addons/account_invoice_check_picking_date/static/description/index.html
odoo/addons/account_invoice_check_picking_date/tests/__init__.py
odoo/addons/account_invoice_check_picking_date/wizards/__init__.py
odoo/addons/account_invoice_check_picking_date/wizards/invoice_stock_picking_date_wiz.py
odoo/addons/account_invoice_check_picking_date/wizards/invoice_stock_picking_date_wiz.xml
odoo13_addon_account_invoice_check_picking_date-13.0.2.0.0.dist-info/METADATA
odoo13_addon_account_invoice_check_picking_date-13.0.2.0.0.dist-info/WHEEL
odoo13_addon_account_invoice_check_picking_date-13.0.2.0.0.dist-info/top_level.txt
odoo13_addon_account_invoice_check_picking_date-13.0.2.0.0.dist-info/RECORD
